pySEAFOM/__init__.py
pySEAFOM/self_noise.py
pyseafom-0.1.2.dist-info/licenses/LICENSE
pyseafom-0.1.2.dist-info/METADATA
pyseafom-0.1.2.dist-info/WHEEL
pyseafom-0.1.2.dist-info/top_level.txt
pyseafom-0.1.2.dist-info/RECORD
