Metadata-Version: 2.4
Name: pySEAFOM
Version: 0.1.2
Summary: Performance analysis and testing tools for Distributed Acoustic Sensing (DAS) systems
Home-page: https://github.com/SEAFOM-Fiber-Optic-Monitoring-Group/pySEAFOM
Author: SEAFOM Fiber Optic Monitoring Group
Author-email: SEAFOM Fiber Optic Monitoring Group <your.email@example.com>
License: MIT
Project-URL: Homepage, https://github.com/SEAFOM-Fiber-Optic-Monitoring-Group/pySEAFOM
Project-URL: Documentation, https://github.com/SEAFOM-Fiber-Optic-Monitoring-Group/pySEAFOM
Project-URL: Repository, https://github.com/SEAFOM-Fiber-Optic-Monitoring-Group/pySEAFOM
Project-URL: Issues, https://github.com/SEAFOM-Fiber-Optic-Monitoring-Group/pySEAFOM/issues
Keywords: DAS,distributed acoustic sensing,self-noise,fiber optic,seismic
Classifier: Development Status :: 3 - Alpha
Classifier: Intended Audience :: Science/Research
Classifier: Topic :: Scientific/Engineering :: Physics
Classifier: License :: OSI Approved :: MIT License
Classifier: Programming Language :: Python :: 3
Classifier: Programming Language :: Python :: 3.8
Classifier: Programming Language :: Python :: 3.9
Classifier: Programming Language :: Python :: 3.10
Classifier: Programming Language :: Python :: 3.11
Classifier: Programming Language :: Python :: 3.12
Requires-Python: >=3.8
License-File: LICENSE
Requires-Dist: numpy>=1.20.0
Requires-Dist: scipy>=1.7.0
Requires-Dist: matplotlib>=3.3.0
Provides-Extra: dev
Requires-Dist: pytest>=7.0; extra == "dev"
Requires-Dist: pytest-cov>=3.0; extra == "dev"
Requires-Dist: black>=22.0; extra == "dev"
Requires-Dist: flake8>=4.0; extra == "dev"
Requires-Dist: jupyter>=1.0; extra == "dev"
Dynamic: author
Dynamic: home-page
Dynamic: license-file
Dynamic: requires-python
